[[{"node":0,"time":1},{"node":2,"time":13},{"node":0,"time":26},{"node":3,"time":37}],[{"node":3,"time":7},{"node":0,"time":20},{"node":2,"time":34}],[{"node":4,"time":6},{"node":0,"time":18},{"node":4,"time":30},{"node":0,"time":42}],[{"node":0,"time":9},{"node":4,"time":20},{"node":0,"time":32},{"node":4,"time":43}],[{"node":0,"time":4},{"node":1,"time":16},{"node":0,"time":27},{"node":1,"time":39}],[{"node":0,"time":11},{"node":2,"time":22}],[{"node":2,"time":4},{"node":0,"time":16},{"node":3,"time":27},{"node":0,"time":39}],[{"node":0,"time":2},{"node":1,"time":12},{"node":0,"time":24},{"node":1,"time":34}],[{"node":0,"time":5},{"node":1,"time":23},{"node":0,"time":33},{"node":1,"time":43}],[{"node":0,"time":8},{"node":3,"time":18},{"node":0,"time":28},{"node":3,"time":44}],[{"node":1,"time":6},{"node":0,"time":17},{"node":1,"time":27}]]